setup.py
mbtouch.egg-info/PKG-INFO
mbtouch.egg-info/SOURCES.txt
mbtouch.egg-info/dependency_links.txt
mbtouch.egg-info/not-zip-safe
mbtouch.egg-info/top_level.txt
touch/__init__.py