Metadata-Version: 1.0
Name: mbtouch
Version: 0.1
Summary: Touch files in Python
Home-page: http://hillbillydeluxe.net
Author: Marcus Bowyer
Author-email: booyah@uw.edu
License: Open Source
Platform: UNKNOWN
